cfgexplorer/__init__.py
cfgexplorer/__main__.py
cfgexplorer/annotator.py
cfgexplorer/cli.py
cfgexplorer/endpoint.py
cfgexplorer/explorer.py
cfgexplorer/utils.py
cfgexplorer/static/js/svg-pan-zoom.js
cfgexplorer/templates/index.html
cfg_explorer-0.0.2.dist-info/LICENSE
cfg_explorer-0.0.2.dist-info/METADATA
cfg_explorer-0.0.2.dist-info/WHEEL
cfg_explorer-0.0.2.dist-info/entry_points.txt
cfg_explorer-0.0.2.dist-info/top_level.txt
cfg_explorer-0.0.2.dist-info/RECORD
