Metadata-Version: 2.1
Name: cfg-explorer
Version: 0.0.2
Summary: CFG explorer
Home-page: https://github.com/axt/cfg-explorer
Author: Attila Axt
Author-email: axt@load.hu
License: UNKNOWN
Platform: UNKNOWN
Classifier: Programming Language :: Python :: 3.5
Classifier: Programming Language :: Python :: 3.6
Classifier: Programming Language :: Python :: 3.7
Classifier: Operating System :: POSIX :: Linux
Classifier: License :: OSI Approved :: BSD License
Requires-Dist: argparse
Requires-Dist: angr
Requires-Dist: bingraphvis
Requires-Dist: flask
